magazine/__init__.py
magazine/io.py
magazine/magazine.py
magazine/publish.py
magazine/fonts/Roboto-Bold.ttf
magazine/fonts/Roboto-Regular.ttf
magazine/fonts/RobotoMono-Bold.ttf
magazine/fonts/RobotoMono-Regular.ttf
magazine-0.4.0.dist-info/licenses/LICENSE
magazine-0.4.0.dist-info/METADATA
magazine-0.4.0.dist-info/WHEEL
magazine-0.4.0.dist-info/top_level.txt
magazine-0.4.0.dist-info/RECORD
