Metadata-Version: 2.4
Name: Magazine
Version: 0.4.0
Summary: Let your code take comprehensive notes and publish notes and figures as a beautiful consolidated PDF document.
Author-email: Martin Schrön <martin@schroen.eu>
License-Expression: MIT
Project-URL: Homepage, https://github.com/mschroen/magazine
Project-URL: Repository, https://github.com/mschroen/magazine
Project-URL: Issues, https://github.com/mschroen/magazine/issues
Keywords: logging,reports,pdf
Requires-Python: >=3.10
License-File: LICENSE
Requires-Dist: numpy<3.0,>=1.20
Requires-Dist: matplotlib>=3.0
Requires-Dist: neatlogger>=0.1
Requires-Dist: pandas
Requires-Dist: fpdf2
Requires-Dist: habanero
Requires-Dist: figurex>=0.2.15
Provides-Extra: dev
Requires-Dist: pytest>3.0; extra == "dev"
Dynamic: license-file
